LICENSE
README.md
setup.cfg
setup.py
camerasimulatordb/__init__.py
camerasimulatordb/baseProcessor.py
camerasimulatordb/lens.py
camerasimulatordb/sensor.py
camerasimulatordb.egg-info/PKG-INFO
camerasimulatordb.egg-info/SOURCES.txt
camerasimulatordb.egg-info/dependency_links.txt
camerasimulatordb.egg-info/entry_points.txt
camerasimulatordb.egg-info/requires.txt
camerasimulatordb.egg-info/top_level.txt
tests/__init__.py
tests/context.py
tests/test_lens.py
tests/test_sensor.py
utils/__init__.py
utils/concurrent_util.py
utils/util.py